MANIFEST.in
README.md
conda_environment.yaml
requirements.txt
setup.py
ibl_to_nwb/__init__.py
ibl_to_nwb.egg-info/PKG-INFO
ibl_to_nwb.egg-info/SOURCES.txt
ibl_to_nwb.egg-info/dependency_links.txt
ibl_to_nwb.egg-info/requires.txt
ibl_to_nwb.egg-info/top_level.txt