Metadata-Version: 2.1
Name: ibl-to-nwb
Version: 0.1.0
Summary: Tools to convert IBL data to NWB format
Home-page: https://github.com/catalystneuro/IBL-to-nwb
Author: Saksham Sharda, Ben Dichter
Author-email: saksham20.sharda@gmail.com
License: UNKNOWN
Keywords: nwb,ibl
Platform: UNKNOWN
Requires-Python: >=3.6
